LICENSE
MANIFEST.in
README.rst
setup.py
impayident/__init__.py
impayident/api.py
impayident/const.py
impayident/core.py
impayident/env.py
impayident/exc.py
impayident/lib.py
impayident/version.txt
impayident.egg-info/PKG-INFO
impayident.egg-info/SOURCES.txt
impayident.egg-info/dependency_links.txt
impayident.egg-info/requires.txt
impayident.egg-info/top_level.txt