Metadata-Version: 1.1
Name: impayident
Version: 0.1.0
Summary: Impay Identification tool.
Home-page: https://github.com/bpc/impayident
Author: Jeong YunWon
Author-email: jeong+impayident@youknowone.org
License: UNKNOWN
Platform: UNKNOWN
Classifier: Intended Audience :: Developers
Classifier: Operating System :: OS Independent
Classifier: Programming Language :: Python
Classifier: Programming Language :: Python :: 2
Classifier: Programming Language :: Python :: 2.7
